jdisk/__init__.py
jdisk/constants.py
jdisk/jdisk.py
jdisk/api/__init__.py
jdisk/api/auth.py
jdisk/api/client.py
jdisk/api/endpoints.py
jdisk/api/files.py
jdisk/cli/__init__.py
jdisk/cli/commands.py
jdisk/cli/main.py
jdisk/cli/utils.py
jdisk/core/__init__.py
jdisk/core/config.py
jdisk/core/operations.py
jdisk/core/session.py
jdisk/models/__init__.py
jdisk/models/data.py
jdisk/models/requests.py
jdisk/models/responses.py
jdisk/services/__init__.py
jdisk/services/auth_service.py
jdisk/services/downloader.py
jdisk/services/file_client.py
jdisk/services/uploader.py
jdisk/utils/__init__.py
jdisk/utils/errors.py
jdisk/utils/helpers.py
jdisk/utils/validators.py
jdisk-0.3.2.dist-info/METADATA
jdisk-0.3.2.dist-info/WHEEL
jdisk-0.3.2.dist-info/entry_points.txt
jdisk-0.3.2.dist-info/licenses/LICENSE
jdisk-0.3.2.dist-info/RECORD
