Metadata-Version: 2.4
Name: jdisk
Version: 0.3.2
Summary: A CLI tool for SJTU Netdisk
Project-URL: Homepage, https://github.com/chengjilai/jdisk
Project-URL: Repository, https://github.com/chengjilai/jdisk
Project-URL: Issues, https://github.com/chengjilai/jdisk/issues
Author-email: chenghjilai <chengjilai@sjtu.edu.cn>
License: MIT
License-File: LICENSE
Keywords: cli,shanghai-jiao-tong-university,storage
Classifier: Intended Audience :: Education
Classifier: License :: OSI Approved :: MIT License
Classifier: Topic :: Internet :: File Transfer Protocol (FTP)
Classifier: Topic :: Utilities
Requires-Python: >=3.9
Requires-Dist: qrcode
Requires-Dist: requests
Requires-Dist: websocket-client
